LICENSE.txt
README.md
setup.cfg
setup.py
pyprover/__coconut__.py
pyprover/__init__.py
pyprover/atoms.py
pyprover/constants.py
pyprover/logic.py
pyprover/parser.py
pyprover/tests.py
pyprover/tools.py
pyprover/util.py
pyprover_px.egg-info/PKG-INFO
pyprover_px.egg-info/SOURCES.txt
pyprover_px.egg-info/dependency_links.txt
pyprover_px.egg-info/requires.txt
pyprover_px.egg-info/top_level.txt