Metadata-Version: 2.1
Name: pyprover-px
Version: 0.5.4
Summary: Fork of pyprover, https://github.com/evhub/pyprover
Home-page: https://github.com/vineetvermait/pyprover
Author: Vineet Verma (Original: Evan Hubinger)
Author-email: vineetverma.it@gmail.com
License: UNKNOWN
Platform: UNKNOWN
Classifier: Development Status :: 3 - Alpha
Classifier: License :: OSI Approved :: Apache Software License
Classifier: Topic :: Software Development :: Libraries :: Python Modules
Classifier: Operating System :: OS Independent
License-File: LICENSE.txt
